freshmail/__init__.py
freshmail/exceptions.py
freshmail/messaging/__init__.py
freshmail/messaging/email/__init__.py
freshmail/messaging/email/attachment.py
freshmail/messaging/email/mailbag.py
freshmail/sender/__init__.py
freshmail/sender/sender.py
freshmail/transport/__init__.py
freshmail/transport/request_executor.py
freshmail/transport/api/__init__.py
freshmail/transport/api/email.py
freshmail_api-1.2.dist-info/METADATA
freshmail_api-1.2.dist-info/WHEEL
freshmail_api-1.2.dist-info/top_level.txt
freshmail_api-1.2.dist-info/RECORD
